get_ncbi/__init__.py
get_ncbi/main.py
get_ncbi-1.1.0.data/scripts/get_ncbi
get_ncbi-1.1.0.dist-info/LICENSE
get_ncbi-1.1.0.dist-info/METADATA
get_ncbi-1.1.0.dist-info/WHEEL
get_ncbi-1.1.0.dist-info/top_level.txt
get_ncbi-1.1.0.dist-info/RECORD
