Metadata-Version: 2.1
Name: get-ncbi
Version: 1.1.0
Summary: Package for distribution
Home-page: UNKNOWN
Author: msjeon27
Author-email: msjeon27@cau.ac.kr
License: UNKNOWN
Keywords: GETNCBI,getncbi
Platform: UNKNOWN
Classifier: Programming Language :: Python :: 3
Classifier: License :: OSI Approved :: MIT License
Classifier: Operating System :: OS Independent
Requires-Python: >=3.6
Requires-Dist: argparse
Requires-Dist: bs4
